<?xml version="1.0" encoding="utf-8"?>
<django-objects version="1.0"><object model="collector.allianceref" pk="1"><field name="reference" type="CharField">Royale House Decados</field><field name="category" type="CharField">nobility</field><field name="color_front" type="CharField">#7ED315</field><field name="color_back" type="CharField">#000000</field><field name="color_highlight" type="CharField">#FFC34A</field><field name="faction" type="CharField"></field><field name="icon_simple" type="CharField">C</field><field name="icon_complex" type="CharField"></field><field name="color_icon_stroke" type="CharField">#3B6A3B</field><field name="color_icon_fill" type="CharField">#61AD5F</field><field name="common_occult_pathes" type="CharField"></field></object><object model="collector.allianceref" pk="2"><field name="reference" type="CharField">Royale House Hawkwood</field><field name="category" type="CharField">nobility</field><field name="color_front" type="CharField">#0C598C</field><field name="color_back" type="CharField">#292929</field><field name="color_highlight" type="CharField">#D9D9D9</field><field name="faction" type="CharField"></field><field name="icon_simple" type="CharField">B</field><field name="icon_complex" type="CharField"></field><field name="color_icon_stroke" type="CharField">#0F0F0F</field><field name="color_icon_fill" type="CharField">#EAD11B</field><field name="common_occult_pathes" type="CharField"></field></object><object model="collector.allianceref" pk="3"><field name="reference" type="CharField">Royale House Hazat</field><field name="category" type="CharField">nobility</field><field name="color_front" type="CharField">#D91F1A</field><field name="color_back" type="CharField">#191A17</field><field name="color_highlight" type="CharField">#FFFFFF</field><field name="faction" type="CharField"></field><field name="icon_simple" type="CharField">D</field><field name="icon_complex" type="CharField"></field><field name="color_icon_stroke" type="CharField">#808080</field><field name="color_icon_fill" type="CharField">#FFFFFF</field><field name="common_occult_pathes" type="CharField"></field></object><object model="collector.allianceref" pk="4"><field name="reference" type="CharField">Royale House Li Halan</field><field name="category" type="CharField">nobility</field><field name="color_front" type="CharField">#AB629D</field><field name="color_back" type="CharField">#DDDBD7</field><field name="color_highlight" type="CharField">#653D74</field><field name="faction" type="CharField"></field><field name="icon_simple" type="CharField">E</field><field name="icon_complex" type="CharField"></field><field name="color_icon_stroke" type="CharField">#BCBCBC</field><field name="color_icon_fill" type="CharField">#FFFFFF</field><field name="common_occult_pathes" type="CharField"></field></object><object model="collector.allianceref" pk="5"><field name="reference" type="CharField">Royale House Al-Malik</field><field name="category" type="CharField">nobility</field><field name="color_front" type="CharField">#9C59BB</field><field name="color_back" type="CharField">#5CB46D</field><field name="color_highlight" type="CharField">#F7FFA9</field><field name="faction" type="CharField"></field><field name="icon_simple" type="CharField">F</field><field name="icon_complex" type="CharField"></field><field name="color_icon_stroke" type="CharField">#DEDEDE</field><field name="color_icon_fill" type="CharField">#FFFFFF</field><field name="common_occult_pathes" type="CharField"></field></object><object model="collector.allianceref" pk="6"><field name="reference" type="CharField">House D'Rouge-Glace</field><field name="category" type="CharField">minor_nobility</field><field name="color_front" type="CharField">#BB444A</field><field name="color_back" type="CharField">#44191B</field><field name="color_highlight" type="CharField">#111111</field><field name="faction" type="CharField"></field><field name="icon_simple" type="CharField">Z</field><field name="icon_complex" type="CharField"></field><field name="color_icon_stroke" type="CharField">#3E3E3E</field><field name="color_icon_fill" type="CharField">#DDDDDD</field><field name="common_occult_pathes" type="CharField"></field></object><object model="collector.allianceref" pk="7"><field name="reference" type="CharField">House Masseri</field><field name="category" type="CharField">minor_nobility</field><field name="color_front" type="CharField">#7D4A1A</field><field name="color_back" type="CharField">#F16510</field><field name="color_highlight" type="CharField">#111111</field><field name="faction" type="CharField"></field><field name="icon_simple" type="CharField">i</field><field name="icon_complex" type="CharField"></field><field name="color_icon_stroke" type="CharField">#A6A6A6</field><field name="color_icon_fill" type="CharField">#F6E13F</field><field name="common_occult_pathes" type="CharField"></field></object><object model="collector.allianceref" pk="8"><field name="reference" type="CharField">Charioteers</field><field name="category" type="CharField">guild</field><field name="color_front" type="CharField">#939393</field><field name="color_back" type="CharField">#FA941E</field><field name="color_highlight" type="CharField">#FFFFFF</field><field name="faction" type="CharField"></field><field name="icon_simple" type="CharField">M</field><field name="icon_complex" type="CharField"></field><field name="color_icon_stroke" type="CharField">#808080</field><field name="color_icon_fill" type="CharField">#101010</field><field name="common_occult_pathes" type="CharField"></field></object><object model="collector.allianceref" pk="9"><field name="reference" type="CharField">Musters</field><field name="category" type="CharField">guild</field><field name="color_front" type="CharField">#939393</field><field name="color_back" type="CharField">#26AFB2</field><field name="color_highlight" type="CharField">#111111</field><field name="faction" type="CharField"></field><field name="icon_simple" type="CharField">P</field><field name="icon_complex" type="CharField"></field><field name="color_icon_stroke" type="CharField">#434343</field><field name="color_icon_fill" type="CharField">#0A0A0A</field><field name="common_occult_pathes" type="CharField"></field></object><object model="collector.allianceref" pk="10"><field name="reference" type="CharField">Reeves</field><field name="category" type="CharField">guild</field><field name="color_front" type="CharField">#939393</field><field name="color_back" type="CharField">#A6C8A3</field><field name="color_highlight" type="CharField">#111111</field><field name="faction" type="CharField"></field><field name="icon_simple" type="CharField">Q</field><field name="icon_complex" type="CharField"></field><field name="color_icon_stroke" type="CharField">#D4CA2B</field><field name="color_icon_fill" type="CharField">#F2F570</field><field name="common_occult_pathes" type="CharField"></field></object><object model="collector.allianceref" pk="11"><field name="reference" type="CharField">Scravers</field><field name="category" type="CharField">guild</field><field name="color_front" type="CharField">#939393</field><field name="color_back" type="CharField">#4C5E4D</field><field name="color_highlight" type="CharField">#111111</field><field name="faction" type="CharField"></field><field name="icon_simple" type="CharField">O</field><field name="icon_complex" type="CharField"></field><field name="color_icon_stroke" type="CharField">#E5E5E5</field><field name="color_icon_fill" type="CharField">#FFFFFF</field><field name="common_occult_pathes" type="CharField"></field></object><object model="collector.allianceref" pk="12"><field name="reference" type="CharField">Brother Battle</field><field name="category" type="CharField">church</field><field name="color_front" type="CharField">#184978</field><field name="color_back" type="CharField">#2C89E0</field><field name="color_highlight" type="CharField">#111111</field><field name="faction" type="CharField"></field><field name="icon_simple" type="CharField">H</field><field name="icon_complex" type="CharField"></field><field name="color_icon_stroke" type="CharField">#888888</field><field name="color_icon_fill" type="CharField">#FFFFFF</field><field name="common_occult_pathes" type="CharField">Brother Battle Rituals, Church Rituals</field></object><object model="collector.allianceref" pk="13"><field name="reference" type="CharField">Eskatonic Order</field><field name="category" type="CharField">church</field><field name="color_front" type="CharField">#184978</field><field name="color_back" type="CharField">#2C89E0</field><field name="color_highlight" type="CharField">#111111</field><field name="faction" type="CharField"></field><field name="icon_simple" type="CharField">I</field><field name="icon_complex" type="CharField"></field><field name="color_icon_stroke" type="CharField">#7B7342</field><field name="color_icon_fill" type="CharField">#FFFFFF</field><field name="common_occult_pathes" type="CharField">Eskatonic Rituals, Church Rituals</field></object><object model="collector.allianceref" pk="14"><field name="reference" type="CharField">Temple Avesti</field><field name="category" type="CharField">church</field><field name="color_front" type="CharField">#184978</field><field name="color_back" type="CharField">#2C89E0</field><field name="color_highlight" type="CharField">#111111</field><field name="faction" type="CharField"></field><field name="icon_simple" type="CharField">J</field><field name="icon_complex" type="CharField"></field><field name="color_icon_stroke" type="CharField">#EAEAEA</field><field name="color_icon_fill" type="CharField">#ECECEC</field><field name="common_occult_pathes" type="CharField">Avestites Rituals, Church Rituals</field></object><object model="collector.allianceref" pk="15"><field name="reference" type="CharField">Sanctuary Aeon</field><field name="category" type="CharField">church</field><field name="color_front" type="CharField">#184978</field><field name="color_back" type="CharField">#2C89E0</field><field name="color_highlight" type="CharField">#111111</field><field name="faction" type="CharField"></field><field name="icon_simple" type="CharField">K</field><field name="icon_complex" type="CharField"></field><field name="color_icon_stroke" type="CharField">#F1E647</field><field name="color_icon_fill" type="CharField">#C8BF3B</field><field name="common_occult_pathes" type="CharField">Amalthean Rituals, Church Rituals, Chapter Rituals</field></object><object model="collector.allianceref" pk="16"><field name="reference" type="CharField">House Van Gelder</field><field name="category" type="CharField">minor_nobility</field><field name="color_front" type="CharField">#AAAAAA</field><field name="color_back" type="CharField">#666666</field><field name="color_highlight" type="CharField">#111111</field><field name="faction" type="CharField"></field><field name="icon_simple" type="CharField">n</field><field name="icon_complex" type="CharField"></field><field name="color_icon_stroke" type="CharField">#888888</field><field name="color_icon_fill" type="CharField">#333333</field><field name="common_occult_pathes" type="CharField"></field></object><object model="collector.allianceref" pk="17"><field name="reference" type="CharField">House Alecto</field><field name="category" type="CharField">minor_nobility</field><field name="color_front" type="CharField">#8D508E</field><field name="color_back" type="CharField">#4F2266</field><field name="color_highlight" type="CharField">#111111</field><field name="faction" type="CharField"></field><field name="icon_simple" type="CharField">l</field><field name="icon_complex" type="CharField"></field><field name="color_icon_stroke" type="CharField">#EDEDED</field><field name="color_icon_fill" type="CharField">#FFFFFF</field><field name="common_occult_pathes" type="CharField"></field></object><object model="collector.allianceref" pk="18"><field name="reference" type="CharField">House Juandaastas</field><field name="category" type="CharField">minor_nobility</field><field name="color_front" type="CharField">#C8CA48</field><field name="color_back" type="CharField">#9CC0AB</field><field name="color_highlight" type="CharField">#111111</field><field name="faction" type="CharField"></field><field name="icon_simple" type="CharField">f</field><field name="icon_complex" type="CharField"></field><field name="color_icon_stroke" type="CharField">#4D4D4D</field><field name="color_icon_fill" type="CharField">#181818</field><field name="common_occult_pathes" type="CharField"></field></object><object model="collector.allianceref" pk="19"><field name="reference" type="CharField">House Justinian</field><field name="category" type="CharField">minor_nobility</field><field name="color_front" type="CharField">#19AAAA</field><field name="color_back" type="CharField">#F5E43D</field><field name="color_highlight" type="CharField">#111111</field><field name="faction" type="CharField"></field><field name="icon_simple" type="CharField">g</field><field name="icon_complex" type="CharField"></field><field name="color_icon_stroke" type="CharField">#888888</field><field name="color_icon_fill" type="CharField">#333333</field><field name="common_occult_pathes" type="CharField"></field></object><object model="collector.allianceref" pk="20"><field name="reference" type="CharField">Le Métier</field><field name="category" type="CharField">minor_guild</field><field name="color_front" type="CharField">#AA8927</field><field name="color_back" type="CharField">#EAE1D6</field><field name="color_highlight" type="CharField">#111111</field><field name="faction" type="CharField"></field><field name="icon_simple" type="CharField">L</field><field name="icon_complex" type="CharField"></field><field name="color_icon_stroke" type="CharField">#888888</field><field name="color_icon_fill" type="CharField">#333333</field><field name="common_occult_pathes" type="CharField"></field></object><object model="collector.allianceref" pk="21"><field name="reference" type="CharField">Emperor Alexius Primus</field><field name="category" type="CharField">nobility</field><field name="color_front" type="CharField">#F8F8F8</field><field name="color_back" type="CharField">#FCFCFC</field><field name="color_highlight" type="CharField">#111111</field><field name="faction" type="CharField"></field><field name="icon_simple" type="CharField">A</field><field name="icon_complex" type="CharField"></field><field name="color_icon_stroke" type="CharField">#606060</field><field name="color_icon_fill" type="CharField">#000000</field><field name="common_occult_pathes" type="CharField"></field></object><object model="collector.allianceref" pk="22"><field name="reference" type="CharField">Le Masque</field><field name="category" type="CharField">minor_guild</field><field name="color_front" type="CharField">#EC57E3</field><field name="color_back" type="CharField">#844275</field><field name="color_highlight" type="CharField">#111111</field><field name="faction" type="CharField"></field><field name="icon_simple" type="CharField">L</field><field name="icon_complex" type="CharField"></field><field name="color_icon_stroke" type="CharField">#F8F8F8</field><field name="color_icon_fill" type="CharField">#CDCDCD</field><field name="common_occult_pathes" type="CharField"></field></object><object model="collector.allianceref" pk="23"><field name="reference" type="CharField">Orthodox Church</field><field name="category" type="CharField">church</field><field name="color_front" type="CharField">#184978</field><field name="color_back" type="CharField">#2C89E0</field><field name="color_highlight" type="CharField">#111111</field><field name="faction" type="CharField"></field><field name="icon_simple" type="CharField">G</field><field name="icon_complex" type="CharField"></field><field name="color_icon_stroke" type="CharField">#0E0E0E</field><field name="color_icon_fill" type="CharField">#FFFFFF</field><field name="common_occult_pathes" type="CharField">Orthodox Rituals, Church Rituals</field></object><object model="collector.allianceref" pk="24"><field name="reference" type="CharField">House Keddah</field><field name="category" type="CharField">minor_nobility</field><field name="color_front" type="CharField">#BC795A</field><field name="color_back" type="CharField">#D83333</field><field name="color_highlight" type="CharField">#111111</field><field name="faction" type="CharField"></field><field name="icon_simple" type="CharField">h</field><field name="icon_complex" type="CharField"></field><field name="color_icon_stroke" type="CharField">#F1F1F1</field><field name="color_icon_fill" type="CharField">#FFFFFF</field><field name="common_occult_pathes" type="CharField"></field></object><object model="collector.allianceref" pk="25"><field name="reference" type="CharField">Engineers</field><field name="category" type="CharField">guild</field><field name="color_front" type="CharField">#939393</field><field name="color_back" type="CharField">#5C4E90</field><field name="color_highlight" type="CharField">#111111</field><field name="faction" type="CharField"></field><field name="icon_simple" type="CharField">N</field><field name="icon_complex" type="CharField"></field><field name="color_icon_stroke" type="CharField">#F0F0F0</field><field name="color_icon_fill" type="CharField">#4A4A4A</field><field name="common_occult_pathes" type="CharField"></field></object><object model="collector.allianceref" pk="26"><field name="reference" type="CharField">Caliphate of Kurga</field><field name="category" type="CharField">foes</field><field name="color_front" type="CharField">#E08924</field><field name="color_back" type="CharField">#E0C024</field><field name="color_highlight" type="CharField">#D30D47</field><field name="faction" type="CharField"></field><field name="icon_simple" type="CharField"></field><field name="icon_complex" type="CharField">kurgan</field><field name="color_icon_stroke" type="CharField">#444444</field><field name="color_icon_fill" type="CharField">#161616</field><field name="common_occult_pathes" type="CharField"></field></object><object model="collector.allianceref" pk="27"><field name="reference" type="CharField">Vuldrok Star Nations</field><field name="category" type="CharField">foes</field><field name="color_front" type="CharField">#AAAAAA</field><field name="color_back" type="CharField">#666666</field><field name="color_highlight" type="CharField">#111111</field><field name="faction" type="CharField"></field><field name="icon_simple" type="CharField">X</field><field name="icon_complex" type="CharField"></field><field name="color_icon_stroke" type="CharField">#888888</field><field name="color_icon_fill" type="CharField">#333333</field><field name="common_occult_pathes" type="CharField"></field></object><object model="collector.allianceref" pk="28"><field name="reference" type="CharField">Vau Hegemony</field><field name="category" type="CharField">foes</field><field name="color_front" type="CharField">#AA9A81</field><field name="color_back" type="CharField">#595144</field><field name="color_highlight" type="CharField">#111111</field><field name="faction" type="CharField"></field><field name="icon_simple" type="CharField">U</field><field name="icon_complex" type="CharField"></field><field name="color_icon_stroke" type="CharField">#888888</field><field name="color_icon_fill" type="CharField">#333333</field><field name="common_occult_pathes" type="CharField"></field></object><object model="collector.allianceref" pk="29"><field name="reference" type="CharField">Favyana</field><field name="category" type="CharField">outlaw</field><field name="color_front" type="CharField">#AAAAAA</field><field name="color_back" type="CharField">#666666</field><field name="color_highlight" type="CharField">#111111</field><field name="faction" type="CharField"></field><field name="icon_simple" type="CharField"></field><field name="icon_complex" type="CharField"></field><field name="color_icon_stroke" type="CharField">#888888</field><field name="color_icon_fill" type="CharField">#333333</field><field name="common_occult_pathes" type="CharField"></field></object><object model="collector.allianceref" pk="30"><field name="reference" type="CharField">Invisible Path</field><field name="category" type="CharField">outlaw</field><field name="color_front" type="CharField">#AAAAAA</field><field name="color_back" type="CharField">#666666</field><field name="color_highlight" type="CharField">#111111</field><field name="faction" type="CharField"></field><field name="icon_simple" type="CharField"></field><field name="icon_complex" type="CharField"></field><field name="color_icon_stroke" type="CharField">#888888</field><field name="color_icon_fill" type="CharField">#333333</field><field name="common_occult_pathes" type="CharField"></field></object><object model="collector.allianceref" pk="31"><field name="reference" type="CharField">Slayers</field><field name="category" type="CharField">minor_guild</field><field name="color_front" type="CharField">#AAAAAA</field><field name="color_back" type="CharField">#666666</field><field name="color_highlight" type="CharField">#111111</field><field name="faction" type="CharField"></field><field name="icon_simple" type="CharField"></field><field name="icon_complex" type="CharField"></field><field name="color_icon_stroke" type="CharField">#888888</field><field name="color_icon_fill" type="CharField">#333333</field><field name="common_occult_pathes" type="CharField"></field></object><object model="collector.allianceref" pk="32"><field name="reference" type="CharField">Bava!</field><field name="category" type="CharField">outlaw</field><field name="color_front" type="CharField">#AAAAAA</field><field name="color_back" type="CharField">#666666</field><field name="color_highlight" type="CharField">#111111</field><field name="faction" type="CharField"></field><field name="icon_simple" type="CharField"></field><field name="icon_complex" type="CharField"></field><field name="color_icon_stroke" type="CharField">#888888</field><field name="color_icon_fill" type="CharField">#333333</field><field name="common_occult_pathes" type="CharField"></field></object><object model="collector.allianceref" pk="33"><field name="reference" type="CharField">House Torenson</field><field name="category" type="CharField">minor_nobility</field><field name="color_front" type="CharField">#AAAAAA</field><field name="color_back" type="CharField">#666666</field><field name="color_highlight" type="CharField">#111111</field><field name="faction" type="CharField"></field><field name="icon_simple" type="CharField"></field><field name="icon_complex" type="CharField"></field><field name="color_icon_stroke" type="CharField">#888888</field><field name="color_icon_fill" type="CharField">#333333</field><field name="common_occult_pathes" type="CharField"></field></object><object model="collector.allianceref" pk="34"><field name="reference" type="CharField">House Gesar</field><field name="category" type="CharField">minor_nobility</field><field name="color_front" type="CharField">#6D2889</field><field name="color_back" type="CharField">#373366</field><field name="color_highlight" type="CharField">#E9CB38</field><field name="faction" type="CharField"></field><field name="icon_simple" type="CharField"></field><field name="icon_complex" type="CharField">gesar</field><field name="color_icon_stroke" type="CharField">#888888</field><field name="color_icon_fill" type="CharField">#333333</field><field name="common_occult_pathes" type="CharField"></field></object><object model="collector.allianceref" pk="35"><field name="reference" type="CharField">Celestial Sun</field><field name="category" type="CharField">other</field><field name="color_front" type="CharField">#AAAAAA</field><field name="color_back" type="CharField">#666666</field><field name="color_highlight" type="CharField">#111111</field><field name="faction" type="CharField"></field><field name="icon_simple" type="CharField"></field><field name="icon_complex" type="CharField"></field><field name="color_icon_stroke" type="CharField">#888888</field><field name="color_icon_fill" type="CharField">#333333</field><field name="common_occult_pathes" type="CharField"></field></object><object model="collector.allianceref" pk="36"><field name="reference" type="CharField">Dark Between the Stars</field><field name="category" type="CharField">other</field><field name="color_front" type="CharField">#AAAAAA</field><field name="color_back" type="CharField">#666666</field><field name="color_highlight" type="CharField">#111111</field><field name="faction" type="CharField"></field><field name="icon_simple" type="CharField"></field><field name="icon_complex" type="CharField"></field><field name="color_icon_stroke" type="CharField">#888888</field><field name="color_icon_fill" type="CharField">#333333</field><field name="common_occult_pathes" type="CharField"></field></object><object model="collector.allianceref" pk="37"><field name="reference" type="CharField">Hesychast Priest</field><field name="category" type="CharField">minor_sects</field><field name="color_front" type="CharField">#AAAAAA</field><field name="color_back" type="CharField">#666666</field><field name="color_highlight" type="CharField">#111111</field><field name="faction" type="CharField"></field><field name="icon_simple" type="CharField"></field><field name="icon_complex" type="CharField"></field><field name="color_icon_stroke" type="CharField">#888888</field><field name="color_icon_fill" type="CharField">#333333</field><field name="common_occult_pathes" type="CharField"></field></object><object model="collector.allianceref" pk="38"><field name="reference" type="CharField">House Medici</field><field name="category" type="CharField">minor_nobility</field><field name="color_front" type="CharField">#6F2A4A</field><field name="color_back" type="CharField">#CC6D1E</field><field name="color_highlight" type="CharField">#111111</field><field name="faction" type="CharField"></field><field name="icon_simple" type="CharField">j</field><field name="icon_complex" type="CharField"></field><field name="color_icon_stroke" type="CharField">#3E3208</field><field name="color_icon_fill" type="CharField">#DDA70B</field><field name="common_occult_pathes" type="CharField"></field></object><object model="collector.allianceref" pk="39"><field name="reference" type="CharField">Chorali</field><field name="category" type="CharField">minor_guild</field><field name="color_front" type="CharField">#AA7B46</field><field name="color_back" type="CharField">#062E66</field><field name="color_highlight" type="CharField">#111111</field><field name="faction" type="CharField"></field><field name="icon_simple" type="CharField">p</field><field name="icon_complex" type="CharField"></field><field name="color_icon_stroke" type="CharField">#888888</field><field name="color_icon_fill" type="CharField">#F0F0F0</field><field name="common_occult_pathes" type="CharField"></field></object><object model="collector.allianceref" pk="40"><field name="reference" type="CharField">House Xanthippe</field><field name="category" type="CharField">minor_nobility</field><field name="color_front" type="CharField">#AAAAAA</field><field name="color_back" type="CharField">#666666</field><field name="color_highlight" type="CharField">#111111</field><field name="faction" type="CharField"></field><field name="icon_simple" type="CharField">o</field><field name="icon_complex" type="CharField"></field><field name="color_icon_stroke" type="CharField">#888888</field><field name="color_icon_fill" type="CharField">#333333</field><field name="common_occult_pathes" type="CharField"></field></object><object model="collector.allianceref" pk="41"><field name="reference" type="CharField">L'Académie</field><field name="category" type="CharField">minor_guild</field><field name="color_front" type="CharField">#AAAAAA</field><field name="color_back" type="CharField">#666666</field><field name="color_highlight" type="CharField">#111111</field><field name="faction" type="CharField"></field><field name="icon_simple" type="CharField">L</field><field name="icon_complex" type="CharField"></field><field name="color_icon_stroke" type="CharField">#888888</field><field name="color_icon_fill" type="CharField">#333333</field><field name="common_occult_pathes" type="CharField"></field></object><object model="collector.allianceref" pk="42"><field name="reference" type="CharField">Blackbone Nomads</field><field name="category" type="CharField">minor_sects</field><field name="color_front" type="CharField">#AAAAAA</field><field name="color_back" type="CharField">#666666</field><field name="color_highlight" type="CharField">#111111</field><field name="faction" type="CharField"></field><field name="icon_simple" type="CharField"></field><field name="icon_complex" type="CharField"></field><field name="color_icon_stroke" type="CharField">#888888</field><field name="color_icon_fill" type="CharField">#333333</field><field name="common_occult_pathes" type="CharField"></field></object><object model="collector.allianceref" pk="43"><field name="reference" type="CharField">Scravers (Van Dyke)</field><field name="category" type="CharField">minor_guild</field><field name="color_front" type="CharField">#6C8BAA</field><field name="color_back" type="CharField">#2A5166</field><field name="color_highlight" type="CharField">#C3C3C3</field><field name="faction" type="CharField">Van Dyke</field><field name="icon_simple" type="CharField"></field><field name="icon_complex" type="CharField"></field><field name="color_icon_stroke" type="CharField">#888888</field><field name="color_icon_fill" type="CharField">#333333</field><field name="common_occult_pathes" type="CharField"></field></object><object model="collector.allianceref" pk="44"><field name="reference" type="CharField">None</field><field name="category" type="CharField">other</field><field name="color_front" type="CharField">#AAAAAA</field><field name="color_back" type="CharField">#666666</field><field name="color_highlight" type="CharField">#111111</field><field name="faction" type="CharField"></field><field name="icon_simple" type="CharField"></field><field name="icon_complex" type="CharField"></field><field name="color_icon_stroke" type="CharField">#888888</field><field name="color_icon_fill" type="CharField">#333333</field><field name="common_occult_pathes" type="CharField"></field></object><object model="collector.allianceref" pk="45"><field name="reference" type="CharField">Mastercert</field><field name="category" type="CharField">foes</field><field name="color_front" type="CharField">#AA0E72</field><field name="color_back" type="CharField">#DDC23D</field><field name="color_highlight" type="CharField">#111111</field><field name="faction" type="CharField"></field><field name="icon_simple" type="CharField"></field><field name="icon_complex" type="CharField"></field><field name="color_icon_stroke" type="CharField">#888888</field><field name="color_icon_fill" type="CharField">#333333</field><field name="common_occult_pathes" type="CharField"></field></object></django-objects>