<?xml version="1.0" encoding="utf-8"?>
<django-objects version="1.0"><object model="collector.blessingcurse" pk="23278"><field name="character" rel="ManyToOneRel" to="collector.character">218</field><field name="blessing_curse_ref" rel="ManyToOneRel" to="collector.blessingcurseref">9</field></object><object model="collector.blessingcurse" pk="23279"><field name="character" rel="ManyToOneRel" to="collector.character">218</field><field name="blessing_curse_ref" rel="ManyToOneRel" to="collector.blessingcurseref">39</field></object><object model="collector.blessingcurse" pk="23280"><field name="character" rel="ManyToOneRel" to="collector.character">23</field><field name="blessing_curse_ref" rel="ManyToOneRel" to="collector.blessingcurseref">47</field></object><object model="collector.blessingcurse" pk="23281"><field name="character" rel="ManyToOneRel" to="collector.character">23</field><field name="blessing_curse_ref" rel="ManyToOneRel" to="collector.blessingcurseref">14</field></object><object model="collector.blessingcurse" pk="23282"><field name="character" rel="ManyToOneRel" to="collector.character">16</field><field name="blessing_curse_ref" rel="ManyToOneRel" to="collector.blessingcurseref">9</field></object><object model="collector.blessingcurse" pk="23283"><field name="character" rel="ManyToOneRel" to="collector.character">16</field><field name="blessing_curse_ref" rel="ManyToOneRel" to="collector.blessingcurseref">34</field></object><object model="collector.blessingcurse" pk="23284"><field name="character" rel="ManyToOneRel" to="collector.character">205</field><field name="blessing_curse_ref" rel="ManyToOneRel" to="collector.blessingcurseref">54</field></object><object model="collector.blessingcurse" pk="23285"><field name="character" rel="ManyToOneRel" to="collector.character">205</field><field name="blessing_curse_ref" rel="ManyToOneRel" to="collector.blessingcurseref">53</field></object><object model="collector.blessingcurse" pk="23286"><field name="character" rel="ManyToOneRel" to="collector.character">205</field><field name="blessing_curse_ref" rel="ManyToOneRel" to="collector.blessingcurseref">55</field></object><object model="collector.blessingcurse" pk="23287"><field name="character" rel="ManyToOneRel" to="collector.character">205</field><field name="blessing_curse_ref" rel="ManyToOneRel" to="collector.blessingcurseref">41</field></object><object model="collector.blessingcurse" pk="23288"><field name="character" rel="ManyToOneRel" to="collector.character">29</field><field name="blessing_curse_ref" rel="ManyToOneRel" to="collector.blessingcurseref">59</field></object><object model="collector.blessingcurse" pk="23289"><field name="character" rel="ManyToOneRel" to="collector.character">29</field><field name="blessing_curse_ref" rel="ManyToOneRel" to="collector.blessingcurseref">36</field></object><object model="collector.blessingcurse" pk="23290"><field name="character" rel="ManyToOneRel" to="collector.character">192</field><field name="blessing_curse_ref" rel="ManyToOneRel" to="collector.blessingcurseref">10</field></object><object model="collector.blessingcurse" pk="23291"><field name="character" rel="ManyToOneRel" to="collector.character">192</field><field name="blessing_curse_ref" rel="ManyToOneRel" to="collector.blessingcurseref">43</field></object><object model="collector.blessingcurse" pk="23292"><field name="character" rel="ManyToOneRel" to="collector.character">58</field><field name="blessing_curse_ref" rel="ManyToOneRel" to="collector.blessingcurseref">17</field></object><object model="collector.blessingcurse" pk="23293"><field name="character" rel="ManyToOneRel" to="collector.character">58</field><field name="blessing_curse_ref" rel="ManyToOneRel" to="collector.blessingcurseref">42</field></object><object model="collector.blessingcurse" pk="23294"><field name="character" rel="ManyToOneRel" to="collector.character">164</field><field name="blessing_curse_ref" rel="ManyToOneRel" to="collector.blessingcurseref">12</field></object><object model="collector.blessingcurse" pk="23295"><field name="character" rel="ManyToOneRel" to="collector.character">164</field><field name="blessing_curse_ref" rel="ManyToOneRel" to="collector.blessingcurseref">57</field></object><object model="collector.blessingcurse" pk="23304"><field name="character" rel="ManyToOneRel" to="collector.character">2</field><field name="blessing_curse_ref" rel="ManyToOneRel" to="collector.blessingcurseref">10</field></object><object model="collector.blessingcurse" pk="23305"><field name="character" rel="ManyToOneRel" to="collector.character">2</field><field name="blessing_curse_ref" rel="ManyToOneRel" to="collector.blessingcurseref">43</field></object><object model="collector.blessingcurse" pk="23306"><field name="character" rel="ManyToOneRel" to="collector.character">2</field><field name="blessing_curse_ref" rel="ManyToOneRel" to="collector.blessingcurseref">50</field></object><object model="collector.blessingcurse" pk="23307"><field name="character" rel="ManyToOneRel" to="collector.character">39</field><field name="blessing_curse_ref" rel="ManyToOneRel" to="collector.blessingcurseref">33</field></object><object model="collector.blessingcurse" pk="23308"><field name="character" rel="ManyToOneRel" to="collector.character">39</field><field name="blessing_curse_ref" rel="ManyToOneRel" to="collector.blessingcurseref">16</field></object><object model="collector.blessingcurse" pk="23309"><field name="character" rel="ManyToOneRel" to="collector.character">6</field><field name="blessing_curse_ref" rel="ManyToOneRel" to="collector.blessingcurseref">15</field></object><object model="collector.blessingcurse" pk="23310"><field name="character" rel="ManyToOneRel" to="collector.character">6</field><field name="blessing_curse_ref" rel="ManyToOneRel" to="collector.blessingcurseref">32</field></object><object model="collector.blessingcurse" pk="23311"><field name="character" rel="ManyToOneRel" to="collector.character">222</field><field name="blessing_curse_ref" rel="ManyToOneRel" to="collector.blessingcurseref">56</field></object><object model="collector.blessingcurse" pk="23312"><field name="character" rel="ManyToOneRel" to="collector.character">222</field><field name="blessing_curse_ref" rel="ManyToOneRel" to="collector.blessingcurseref">15</field></object><object model="collector.blessingcurse" pk="23313"><field name="character" rel="ManyToOneRel" to="collector.character">187</field><field name="blessing_curse_ref" rel="ManyToOneRel" to="collector.blessingcurseref">8</field></object><object model="collector.blessingcurse" pk="23314"><field name="character" rel="ManyToOneRel" to="collector.character">187</field><field name="blessing_curse_ref" rel="ManyToOneRel" to="collector.blessingcurseref">29</field></object><object model="collector.blessingcurse" pk="23315"><field name="character" rel="ManyToOneRel" to="collector.character">217</field><field name="blessing_curse_ref" rel="ManyToOneRel" to="collector.blessingcurseref">7</field></object><object model="collector.blessingcurse" pk="23316"><field name="character" rel="ManyToOneRel" to="collector.character">217</field><field name="blessing_curse_ref" rel="ManyToOneRel" to="collector.blessingcurseref">22</field></object><object model="collector.blessingcurse" pk="23317"><field name="character" rel="ManyToOneRel" to="collector.character">217</field><field name="blessing_curse_ref" rel="ManyToOneRel" to="collector.blessingcurseref">50</field></object><object model="collector.blessingcurse" pk="23318"><field name="character" rel="ManyToOneRel" to="collector.character">212</field><field name="blessing_curse_ref" rel="ManyToOneRel" to="collector.blessingcurseref">59</field></object><object model="collector.blessingcurse" pk="23319"><field name="character" rel="ManyToOneRel" to="collector.character">212</field><field name="blessing_curse_ref" rel="ManyToOneRel" to="collector.blessingcurseref">36</field></object><object model="collector.blessingcurse" pk="23321"><field name="character" rel="ManyToOneRel" to="collector.character">178</field><field name="blessing_curse_ref" rel="ManyToOneRel" to="collector.blessingcurseref">52</field></object><object model="collector.blessingcurse" pk="23322"><field name="character" rel="ManyToOneRel" to="collector.character">178</field><field name="blessing_curse_ref" rel="ManyToOneRel" to="collector.blessingcurseref">51</field></object><object model="collector.blessingcurse" pk="23323"><field name="character" rel="ManyToOneRel" to="collector.character">178</field><field name="blessing_curse_ref" rel="ManyToOneRel" to="collector.blessingcurseref">37</field></object><object model="collector.blessingcurse" pk="23330"><field name="character" rel="ManyToOneRel" to="collector.character">17</field><field name="blessing_curse_ref" rel="ManyToOneRel" to="collector.blessingcurseref">10</field></object><object model="collector.blessingcurse" pk="23331"><field name="character" rel="ManyToOneRel" to="collector.character">17</field><field name="blessing_curse_ref" rel="ManyToOneRel" to="collector.blessingcurseref">43</field></object><object model="collector.blessingcurse" pk="23332"><field name="character" rel="ManyToOneRel" to="collector.character">17</field><field name="blessing_curse_ref" rel="ManyToOneRel" to="collector.blessingcurseref">50</field></object><object model="collector.blessingcurse" pk="23333"><field name="character" rel="ManyToOneRel" to="collector.character">184</field><field name="blessing_curse_ref" rel="ManyToOneRel" to="collector.blessingcurseref">23</field></object><object model="collector.blessingcurse" pk="23334"><field name="character" rel="ManyToOneRel" to="collector.character">184</field><field name="blessing_curse_ref" rel="ManyToOneRel" to="collector.blessingcurseref">10</field></object><object model="collector.blessingcurse" pk="23335"><field name="character" rel="ManyToOneRel" to="collector.character">185</field><field name="blessing_curse_ref" rel="ManyToOneRel" to="collector.blessingcurseref">9</field></object><object model="collector.blessingcurse" pk="23336"><field name="character" rel="ManyToOneRel" to="collector.character">185</field><field name="blessing_curse_ref" rel="ManyToOneRel" to="collector.blessingcurseref">39</field></object><object model="collector.blessingcurse" pk="23337"><field name="character" rel="ManyToOneRel" to="collector.character">185</field><field name="blessing_curse_ref" rel="ManyToOneRel" to="collector.blessingcurseref">50</field></object><object model="collector.blessingcurse" pk="23338"><field name="character" rel="ManyToOneRel" to="collector.character">203</field><field name="blessing_curse_ref" rel="ManyToOneRel" to="collector.blessingcurseref">9</field></object><object model="collector.blessingcurse" pk="23339"><field name="character" rel="ManyToOneRel" to="collector.character">203</field><field name="blessing_curse_ref" rel="ManyToOneRel" to="collector.blessingcurseref">34</field></object><object model="collector.blessingcurse" pk="23340"><field name="character" rel="ManyToOneRel" to="collector.character">98</field><field name="blessing_curse_ref" rel="ManyToOneRel" to="collector.blessingcurseref">33</field></object><object model="collector.blessingcurse" pk="23341"><field name="character" rel="ManyToOneRel" to="collector.character">98</field><field name="blessing_curse_ref" rel="ManyToOneRel" to="collector.blessingcurseref">16</field></object><object model="collector.blessingcurse" pk="23342"><field name="character" rel="ManyToOneRel" to="collector.character">198</field><field name="blessing_curse_ref" rel="ManyToOneRel" to="collector.blessingcurseref">33</field></object><object model="collector.blessingcurse" pk="23343"><field name="character" rel="ManyToOneRel" to="collector.character">198</field><field name="blessing_curse_ref" rel="ManyToOneRel" to="collector.blessingcurseref">16</field></object><object model="collector.blessingcurse" pk="23344"><field name="character" rel="ManyToOneRel" to="collector.character">194</field><field name="blessing_curse_ref" rel="ManyToOneRel" to="collector.blessingcurseref">12</field></object><object model="collector.blessingcurse" pk="23345"><field name="character" rel="ManyToOneRel" to="collector.character">194</field><field name="blessing_curse_ref" rel="ManyToOneRel" to="collector.blessingcurseref">57</field></object><object model="collector.blessingcurse" pk="23346"><field name="character" rel="ManyToOneRel" to="collector.character">197</field><field name="blessing_curse_ref" rel="ManyToOneRel" to="collector.blessingcurseref">11</field></object><object model="collector.blessingcurse" pk="23347"><field name="character" rel="ManyToOneRel" to="collector.character">197</field><field name="blessing_curse_ref" rel="ManyToOneRel" to="collector.blessingcurseref">31</field></object><object model="collector.blessingcurse" pk="23348"><field name="character" rel="ManyToOneRel" to="collector.character">201</field><field name="blessing_curse_ref" rel="ManyToOneRel" to="collector.blessingcurseref">56</field></object><object model="collector.blessingcurse" pk="23349"><field name="character" rel="ManyToOneRel" to="collector.character">201</field><field name="blessing_curse_ref" rel="ManyToOneRel" to="collector.blessingcurseref">15</field></object><object model="collector.blessingcurse" pk="23350"><field name="character" rel="ManyToOneRel" to="collector.character">209</field><field name="blessing_curse_ref" rel="ManyToOneRel" to="collector.blessingcurseref">54</field></object><object model="collector.blessingcurse" pk="23351"><field name="character" rel="ManyToOneRel" to="collector.character">209</field><field name="blessing_curse_ref" rel="ManyToOneRel" to="collector.blessingcurseref">53</field></object><object model="collector.blessingcurse" pk="23352"><field name="character" rel="ManyToOneRel" to="collector.character">209</field><field name="blessing_curse_ref" rel="ManyToOneRel" to="collector.blessingcurseref">55</field></object><object model="collector.blessingcurse" pk="23353"><field name="character" rel="ManyToOneRel" to="collector.character">209</field><field name="blessing_curse_ref" rel="ManyToOneRel" to="collector.blessingcurseref">41</field></object><object model="collector.blessingcurse" pk="23354"><field name="character" rel="ManyToOneRel" to="collector.character">115</field><field name="blessing_curse_ref" rel="ManyToOneRel" to="collector.blessingcurseref">54</field></object><object model="collector.blessingcurse" pk="23355"><field name="character" rel="ManyToOneRel" to="collector.character">115</field><field name="blessing_curse_ref" rel="ManyToOneRel" to="collector.blessingcurseref">53</field></object><object model="collector.blessingcurse" pk="23356"><field name="character" rel="ManyToOneRel" to="collector.character">115</field><field name="blessing_curse_ref" rel="ManyToOneRel" to="collector.blessingcurseref">55</field></object><object model="collector.blessingcurse" pk="23357"><field name="character" rel="ManyToOneRel" to="collector.character">115</field><field name="blessing_curse_ref" rel="ManyToOneRel" to="collector.blessingcurseref">41</field></object><object model="collector.blessingcurse" pk="23358"><field name="character" rel="ManyToOneRel" to="collector.character">191</field><field name="blessing_curse_ref" rel="ManyToOneRel" to="collector.blessingcurseref">37</field></object><object model="collector.blessingcurse" pk="23359"><field name="character" rel="ManyToOneRel" to="collector.character">191</field><field name="blessing_curse_ref" rel="ManyToOneRel" to="collector.blessingcurseref">18</field></object><object model="collector.blessingcurse" pk="23360"><field name="character" rel="ManyToOneRel" to="collector.character">12</field><field name="blessing_curse_ref" rel="ManyToOneRel" to="collector.blessingcurseref">36</field></object><object model="collector.blessingcurse" pk="23361"><field name="character" rel="ManyToOneRel" to="collector.character">12</field><field name="blessing_curse_ref" rel="ManyToOneRel" to="collector.blessingcurseref">58</field></object><object model="collector.blessingcurse" pk="23362"><field name="character" rel="ManyToOneRel" to="collector.character">12</field><field name="blessing_curse_ref" rel="ManyToOneRel" to="collector.blessingcurseref">11</field></object><object model="collector.blessingcurse" pk="23363"><field name="character" rel="ManyToOneRel" to="collector.character">66</field><field name="blessing_curse_ref" rel="ManyToOneRel" to="collector.blessingcurseref">7</field></object><object model="collector.blessingcurse" pk="23364"><field name="character" rel="ManyToOneRel" to="collector.character">66</field><field name="blessing_curse_ref" rel="ManyToOneRel" to="collector.blessingcurseref">22</field></object><object model="collector.blessingcurse" pk="23365"><field name="character" rel="ManyToOneRel" to="collector.character">183</field><field name="blessing_curse_ref" rel="ManyToOneRel" to="collector.blessingcurseref">10</field></object><object model="collector.blessingcurse" pk="23366"><field name="character" rel="ManyToOneRel" to="collector.character">183</field><field name="blessing_curse_ref" rel="ManyToOneRel" to="collector.blessingcurseref">43</field></object><object model="collector.blessingcurse" pk="23367"><field name="character" rel="ManyToOneRel" to="collector.character">183</field><field name="blessing_curse_ref" rel="ManyToOneRel" to="collector.blessingcurseref">50</field></object><object model="collector.blessingcurse" pk="23368"><field name="character" rel="ManyToOneRel" to="collector.character">156</field><field name="blessing_curse_ref" rel="ManyToOneRel" to="collector.blessingcurseref">36</field></object><object model="collector.blessingcurse" pk="23369"><field name="character" rel="ManyToOneRel" to="collector.character">156</field><field name="blessing_curse_ref" rel="ManyToOneRel" to="collector.blessingcurseref">58</field></object><object model="collector.blessingcurse" pk="23370"><field name="character" rel="ManyToOneRel" to="collector.character">181</field><field name="blessing_curse_ref" rel="ManyToOneRel" to="collector.blessingcurseref">9</field></object><object model="collector.blessingcurse" pk="23371"><field name="character" rel="ManyToOneRel" to="collector.character">181</field><field name="blessing_curse_ref" rel="ManyToOneRel" to="collector.blessingcurseref">34</field></object><object model="collector.blessingcurse" pk="23372"><field name="character" rel="ManyToOneRel" to="collector.character">135</field><field name="blessing_curse_ref" rel="ManyToOneRel" to="collector.blessingcurseref">59</field></object><object model="collector.blessingcurse" pk="23373"><field name="character" rel="ManyToOneRel" to="collector.character">135</field><field name="blessing_curse_ref" rel="ManyToOneRel" to="collector.blessingcurseref">36</field></object><object model="collector.blessingcurse" pk="23374"><field name="character" rel="ManyToOneRel" to="collector.character">38</field><field name="blessing_curse_ref" rel="ManyToOneRel" to="collector.blessingcurseref">11</field></object><object model="collector.blessingcurse" pk="23375"><field name="character" rel="ManyToOneRel" to="collector.character">38</field><field name="blessing_curse_ref" rel="ManyToOneRel" to="collector.blessingcurseref">31</field></object><object model="collector.blessingcurse" pk="23376"><field name="character" rel="ManyToOneRel" to="collector.character">207</field><field name="blessing_curse_ref" rel="ManyToOneRel" to="collector.blessingcurseref">54</field></object><object model="collector.blessingcurse" pk="23377"><field name="character" rel="ManyToOneRel" to="collector.character">207</field><field name="blessing_curse_ref" rel="ManyToOneRel" to="collector.blessingcurseref">53</field></object><object model="collector.blessingcurse" pk="23378"><field name="character" rel="ManyToOneRel" to="collector.character">207</field><field name="blessing_curse_ref" rel="ManyToOneRel" to="collector.blessingcurseref">55</field></object><object model="collector.blessingcurse" pk="23379"><field name="character" rel="ManyToOneRel" to="collector.character">207</field><field name="blessing_curse_ref" rel="ManyToOneRel" to="collector.blessingcurseref">41</field></object><object model="collector.blessingcurse" pk="23380"><field name="character" rel="ManyToOneRel" to="collector.character">204</field><field name="blessing_curse_ref" rel="ManyToOneRel" to="collector.blessingcurseref">54</field></object><object model="collector.blessingcurse" pk="23381"><field name="character" rel="ManyToOneRel" to="collector.character">204</field><field name="blessing_curse_ref" rel="ManyToOneRel" to="collector.blessingcurseref">53</field></object><object model="collector.blessingcurse" pk="23382"><field name="character" rel="ManyToOneRel" to="collector.character">204</field><field name="blessing_curse_ref" rel="ManyToOneRel" to="collector.blessingcurseref">55</field></object><object model="collector.blessingcurse" pk="23383"><field name="character" rel="ManyToOneRel" to="collector.character">204</field><field name="blessing_curse_ref" rel="ManyToOneRel" to="collector.blessingcurseref">41</field></object><object model="collector.blessingcurse" pk="23386"><field name="character" rel="ManyToOneRel" to="collector.character">3</field><field name="blessing_curse_ref" rel="ManyToOneRel" to="collector.blessingcurseref">12</field></object><object model="collector.blessingcurse" pk="23387"><field name="character" rel="ManyToOneRel" to="collector.character">3</field><field name="blessing_curse_ref" rel="ManyToOneRel" to="collector.blessingcurseref">57</field></object><object model="collector.blessingcurse" pk="23388"><field name="character" rel="ManyToOneRel" to="collector.character">186</field><field name="blessing_curse_ref" rel="ManyToOneRel" to="collector.blessingcurseref">52</field></object><object model="collector.blessingcurse" pk="23389"><field name="character" rel="ManyToOneRel" to="collector.character">186</field><field name="blessing_curse_ref" rel="ManyToOneRel" to="collector.blessingcurseref">51</field></object><object model="collector.blessingcurse" pk="23390"><field name="character" rel="ManyToOneRel" to="collector.character">186</field><field name="blessing_curse_ref" rel="ManyToOneRel" to="collector.blessingcurseref">53</field></object><object model="collector.blessingcurse" pk="23391"><field name="character" rel="ManyToOneRel" to="collector.character">35</field><field name="blessing_curse_ref" rel="ManyToOneRel" to="collector.blessingcurseref">33</field></object><object model="collector.blessingcurse" pk="23392"><field name="character" rel="ManyToOneRel" to="collector.character">35</field><field name="blessing_curse_ref" rel="ManyToOneRel" to="collector.blessingcurseref">16</field></object><object model="collector.blessingcurse" pk="23395"><field name="character" rel="ManyToOneRel" to="collector.character">169</field><field name="blessing_curse_ref" rel="ManyToOneRel" to="collector.blessingcurseref">37</field></object><object model="collector.blessingcurse" pk="23396"><field name="character" rel="ManyToOneRel" to="collector.character">169</field><field name="blessing_curse_ref" rel="ManyToOneRel" to="collector.blessingcurseref">18</field></object><object model="collector.blessingcurse" pk="23397"><field name="character" rel="ManyToOneRel" to="collector.character">195</field><field name="blessing_curse_ref" rel="ManyToOneRel" to="collector.blessingcurseref">7</field></object><object model="collector.blessingcurse" pk="23398"><field name="character" rel="ManyToOneRel" to="collector.character">195</field><field name="blessing_curse_ref" rel="ManyToOneRel" to="collector.blessingcurseref">22</field></object><object model="collector.blessingcurse" pk="23399"><field name="character" rel="ManyToOneRel" to="collector.character">195</field><field name="blessing_curse_ref" rel="ManyToOneRel" to="collector.blessingcurseref">50</field></object><object model="collector.blessingcurse" pk="23400"><field name="character" rel="ManyToOneRel" to="collector.character">193</field><field name="blessing_curse_ref" rel="ManyToOneRel" to="collector.blessingcurseref">56</field></object><object model="collector.blessingcurse" pk="23401"><field name="character" rel="ManyToOneRel" to="collector.character">193</field><field name="blessing_curse_ref" rel="ManyToOneRel" to="collector.blessingcurseref">15</field></object><object model="collector.blessingcurse" pk="23402"><field name="character" rel="ManyToOneRel" to="collector.character">140</field><field name="blessing_curse_ref" rel="ManyToOneRel" to="collector.blessingcurseref">37</field></object><object model="collector.blessingcurse" pk="23403"><field name="character" rel="ManyToOneRel" to="collector.character">140</field><field name="blessing_curse_ref" rel="ManyToOneRel" to="collector.blessingcurseref">18</field></object><object model="collector.blessingcurse" pk="23404"><field name="character" rel="ManyToOneRel" to="collector.character">7</field><field name="blessing_curse_ref" rel="ManyToOneRel" to="collector.blessingcurseref">33</field></object><object model="collector.blessingcurse" pk="23405"><field name="character" rel="ManyToOneRel" to="collector.character">7</field><field name="blessing_curse_ref" rel="ManyToOneRel" to="collector.blessingcurseref">16</field></object><object model="collector.blessingcurse" pk="23409"><field name="character" rel="ManyToOneRel" to="collector.character">210</field><field name="blessing_curse_ref" rel="ManyToOneRel" to="collector.blessingcurseref">7</field></object><object model="collector.blessingcurse" pk="23410"><field name="character" rel="ManyToOneRel" to="collector.character">210</field><field name="blessing_curse_ref" rel="ManyToOneRel" to="collector.blessingcurseref">22</field></object><object model="collector.blessingcurse" pk="23413"><field name="character" rel="ManyToOneRel" to="collector.character">8</field><field name="blessing_curse_ref" rel="ManyToOneRel" to="collector.blessingcurseref">59</field></object><object model="collector.blessingcurse" pk="23414"><field name="character" rel="ManyToOneRel" to="collector.character">8</field><field name="blessing_curse_ref" rel="ManyToOneRel" to="collector.blessingcurseref">36</field></object><object model="collector.blessingcurse" pk="23415"><field name="character" rel="ManyToOneRel" to="collector.character">200</field><field name="blessing_curse_ref" rel="ManyToOneRel" to="collector.blessingcurseref">23</field></object><object model="collector.blessingcurse" pk="23416"><field name="character" rel="ManyToOneRel" to="collector.character">200</field><field name="blessing_curse_ref" rel="ManyToOneRel" to="collector.blessingcurseref">10</field></object><object model="collector.blessingcurse" pk="23417"><field name="character" rel="ManyToOneRel" to="collector.character">221</field><field name="blessing_curse_ref" rel="ManyToOneRel" to="collector.blessingcurseref">36</field></object><object model="collector.blessingcurse" pk="23418"><field name="character" rel="ManyToOneRel" to="collector.character">221</field><field name="blessing_curse_ref" rel="ManyToOneRel" to="collector.blessingcurseref">58</field></object><object model="collector.blessingcurse" pk="23419"><field name="character" rel="ManyToOneRel" to="collector.character">208</field><field name="blessing_curse_ref" rel="ManyToOneRel" to="collector.blessingcurseref">54</field></object><object model="collector.blessingcurse" pk="23420"><field name="character" rel="ManyToOneRel" to="collector.character">208</field><field name="blessing_curse_ref" rel="ManyToOneRel" to="collector.blessingcurseref">53</field></object><object model="collector.blessingcurse" pk="23421"><field name="character" rel="ManyToOneRel" to="collector.character">208</field><field name="blessing_curse_ref" rel="ManyToOneRel" to="collector.blessingcurseref">55</field></object><object model="collector.blessingcurse" pk="23422"><field name="character" rel="ManyToOneRel" to="collector.character">208</field><field name="blessing_curse_ref" rel="ManyToOneRel" to="collector.blessingcurseref">41</field></object><object model="collector.blessingcurse" pk="23423"><field name="character" rel="ManyToOneRel" to="collector.character">190</field><field name="blessing_curse_ref" rel="ManyToOneRel" to="collector.blessingcurseref">7</field></object><object model="collector.blessingcurse" pk="23424"><field name="character" rel="ManyToOneRel" to="collector.character">190</field><field name="blessing_curse_ref" rel="ManyToOneRel" to="collector.blessingcurseref">22</field></object><object model="collector.blessingcurse" pk="23425"><field name="character" rel="ManyToOneRel" to="collector.character">215</field><field name="blessing_curse_ref" rel="ManyToOneRel" to="collector.blessingcurseref">9</field></object><object model="collector.blessingcurse" pk="23426"><field name="character" rel="ManyToOneRel" to="collector.character">215</field><field name="blessing_curse_ref" rel="ManyToOneRel" to="collector.blessingcurseref">34</field></object><object model="collector.blessingcurse" pk="23427"><field name="character" rel="ManyToOneRel" to="collector.character">76</field><field name="blessing_curse_ref" rel="ManyToOneRel" to="collector.blessingcurseref">33</field></object><object model="collector.blessingcurse" pk="23428"><field name="character" rel="ManyToOneRel" to="collector.character">76</field><field name="blessing_curse_ref" rel="ManyToOneRel" to="collector.blessingcurseref">16</field></object><object model="collector.blessingcurse" pk="23429"><field name="character" rel="ManyToOneRel" to="collector.character">87</field><field name="blessing_curse_ref" rel="ManyToOneRel" to="collector.blessingcurseref">36</field></object><object model="collector.blessingcurse" pk="23430"><field name="character" rel="ManyToOneRel" to="collector.character">87</field><field name="blessing_curse_ref" rel="ManyToOneRel" to="collector.blessingcurseref">58</field></object><object model="collector.blessingcurse" pk="23431"><field name="character" rel="ManyToOneRel" to="collector.character">136</field><field name="blessing_curse_ref" rel="ManyToOneRel" to="collector.blessingcurseref">59</field></object><object model="collector.blessingcurse" pk="23432"><field name="character" rel="ManyToOneRel" to="collector.character">136</field><field name="blessing_curse_ref" rel="ManyToOneRel" to="collector.blessingcurseref">36</field></object><object model="collector.blessingcurse" pk="23433"><field name="character" rel="ManyToOneRel" to="collector.character">136</field><field name="blessing_curse_ref" rel="ManyToOneRel" to="collector.blessingcurseref">3</field></object><object model="collector.blessingcurse" pk="23434"><field name="character" rel="ManyToOneRel" to="collector.character">189</field><field name="blessing_curse_ref" rel="ManyToOneRel" to="collector.blessingcurseref">17</field></object><object model="collector.blessingcurse" pk="23435"><field name="character" rel="ManyToOneRel" to="collector.character">189</field><field name="blessing_curse_ref" rel="ManyToOneRel" to="collector.blessingcurseref">42</field></object><object model="collector.blessingcurse" pk="23436"><field name="character" rel="ManyToOneRel" to="collector.character">189</field><field name="blessing_curse_ref" rel="ManyToOneRel" to="collector.blessingcurseref">2</field></object><object model="collector.blessingcurse" pk="23437"><field name="character" rel="ManyToOneRel" to="collector.character">189</field><field name="blessing_curse_ref" rel="ManyToOneRel" to="collector.blessingcurseref">48</field></object><object model="collector.blessingcurse" pk="23438"><field name="character" rel="ManyToOneRel" to="collector.character">61</field><field name="blessing_curse_ref" rel="ManyToOneRel" to="collector.blessingcurseref">12</field></object><object model="collector.blessingcurse" pk="23439"><field name="character" rel="ManyToOneRel" to="collector.character">61</field><field name="blessing_curse_ref" rel="ManyToOneRel" to="collector.blessingcurseref">57</field></object><object model="collector.blessingcurse" pk="23440"><field name="character" rel="ManyToOneRel" to="collector.character">219</field><field name="blessing_curse_ref" rel="ManyToOneRel" to="collector.blessingcurseref">24</field></object><object model="collector.blessingcurse" pk="23441"><field name="character" rel="ManyToOneRel" to="collector.character">219</field><field name="blessing_curse_ref" rel="ManyToOneRel" to="collector.blessingcurseref">13</field></object><object model="collector.blessingcurse" pk="23445"><field name="character" rel="ManyToOneRel" to="collector.character">180</field><field name="blessing_curse_ref" rel="ManyToOneRel" to="collector.blessingcurseref">28</field></object><object model="collector.blessingcurse" pk="23446"><field name="character" rel="ManyToOneRel" to="collector.character">180</field><field name="blessing_curse_ref" rel="ManyToOneRel" to="collector.blessingcurseref">15</field></object><object model="collector.blessingcurse" pk="23447"><field name="character" rel="ManyToOneRel" to="collector.character">206</field><field name="blessing_curse_ref" rel="ManyToOneRel" to="collector.blessingcurseref">54</field></object><object model="collector.blessingcurse" pk="23448"><field name="character" rel="ManyToOneRel" to="collector.character">206</field><field name="blessing_curse_ref" rel="ManyToOneRel" to="collector.blessingcurseref">53</field></object><object model="collector.blessingcurse" pk="23449"><field name="character" rel="ManyToOneRel" to="collector.character">206</field><field name="blessing_curse_ref" rel="ManyToOneRel" to="collector.blessingcurseref">55</field></object><object model="collector.blessingcurse" pk="23450"><field name="character" rel="ManyToOneRel" to="collector.character">206</field><field name="blessing_curse_ref" rel="ManyToOneRel" to="collector.blessingcurseref">41</field></object><object model="collector.blessingcurse" pk="23453"><field name="character" rel="ManyToOneRel" to="collector.character">24</field><field name="blessing_curse_ref" rel="ManyToOneRel" to="collector.blessingcurseref">9</field></object><object model="collector.blessingcurse" pk="23454"><field name="character" rel="ManyToOneRel" to="collector.character">24</field><field name="blessing_curse_ref" rel="ManyToOneRel" to="collector.blessingcurseref">39</field></object><object model="collector.blessingcurse" pk="23455"><field name="character" rel="ManyToOneRel" to="collector.character">154</field><field name="blessing_curse_ref" rel="ManyToOneRel" to="collector.blessingcurseref">7</field></object><object model="collector.blessingcurse" pk="23456"><field name="character" rel="ManyToOneRel" to="collector.character">154</field><field name="blessing_curse_ref" rel="ManyToOneRel" to="collector.blessingcurseref">22</field></object><object model="collector.blessingcurse" pk="23457"><field name="character" rel="ManyToOneRel" to="collector.character">188</field><field name="blessing_curse_ref" rel="ManyToOneRel" to="collector.blessingcurseref">8</field></object><object model="collector.blessingcurse" pk="23458"><field name="character" rel="ManyToOneRel" to="collector.character">188</field><field name="blessing_curse_ref" rel="ManyToOneRel" to="collector.blessingcurseref">29</field></object><object model="collector.blessingcurse" pk="23459"><field name="character" rel="ManyToOneRel" to="collector.character">59</field><field name="blessing_curse_ref" rel="ManyToOneRel" to="collector.blessingcurseref">56</field></object><object model="collector.blessingcurse" pk="23460"><field name="character" rel="ManyToOneRel" to="collector.character">59</field><field name="blessing_curse_ref" rel="ManyToOneRel" to="collector.blessingcurseref">24</field></object><object model="collector.blessingcurse" pk="23461"><field name="character" rel="ManyToOneRel" to="collector.character">59</field><field name="blessing_curse_ref" rel="ManyToOneRel" to="collector.blessingcurseref">10</field></object><object model="collector.blessingcurse" pk="24098"><field name="character" rel="ManyToOneRel" to="collector.character">11</field><field name="blessing_curse_ref" rel="ManyToOneRel" to="collector.blessingcurseref">54</field></object><object model="collector.blessingcurse" pk="24099"><field name="character" rel="ManyToOneRel" to="collector.character">11</field><field name="blessing_curse_ref" rel="ManyToOneRel" to="collector.blessingcurseref">57</field></object><object model="collector.blessingcurse" pk="24100"><field name="character" rel="ManyToOneRel" to="collector.character">11</field><field name="blessing_curse_ref" rel="ManyToOneRel" to="collector.blessingcurseref">7</field></object><object model="collector.blessingcurse" pk="24101"><field name="character" rel="ManyToOneRel" to="collector.character">11</field><field name="blessing_curse_ref" rel="ManyToOneRel" to="collector.blessingcurseref">22</field></object><object model="collector.blessingcurse" pk="24102"><field name="character" rel="ManyToOneRel" to="collector.character">13</field><field name="blessing_curse_ref" rel="ManyToOneRel" to="collector.blessingcurseref">37</field></object><object model="collector.blessingcurse" pk="24103"><field name="character" rel="ManyToOneRel" to="collector.character">13</field><field name="blessing_curse_ref" rel="ManyToOneRel" to="collector.blessingcurseref">18</field></object><object model="collector.blessingcurse" pk="24104"><field name="character" rel="ManyToOneRel" to="collector.character">20</field><field name="blessing_curse_ref" rel="ManyToOneRel" to="collector.blessingcurseref">37</field></object><object model="collector.blessingcurse" pk="24105"><field name="character" rel="ManyToOneRel" to="collector.character">20</field><field name="blessing_curse_ref" rel="ManyToOneRel" to="collector.blessingcurseref">18</field></object><object model="collector.blessingcurse" pk="24106"><field name="character" rel="ManyToOneRel" to="collector.character">20</field><field name="blessing_curse_ref" rel="ManyToOneRel" to="collector.blessingcurseref">2</field></object><object model="collector.blessingcurse" pk="24107"><field name="character" rel="ManyToOneRel" to="collector.character">22</field><field name="blessing_curse_ref" rel="ManyToOneRel" to="collector.blessingcurseref">13</field></object><object model="collector.blessingcurse" pk="24108"><field name="character" rel="ManyToOneRel" to="collector.character">22</field><field name="blessing_curse_ref" rel="ManyToOneRel" to="collector.blessingcurseref">32</field></object><object model="collector.blessingcurse" pk="24109"><field name="character" rel="ManyToOneRel" to="collector.character">28</field><field name="blessing_curse_ref" rel="ManyToOneRel" to="collector.blessingcurseref">10</field></object><object model="collector.blessingcurse" pk="24110"><field name="character" rel="ManyToOneRel" to="collector.character">28</field><field name="blessing_curse_ref" rel="ManyToOneRel" to="collector.blessingcurseref">43</field></object><object model="collector.blessingcurse" pk="24111"><field name="character" rel="ManyToOneRel" to="collector.character">28</field><field name="blessing_curse_ref" rel="ManyToOneRel" to="collector.blessingcurseref">50</field></object><object model="collector.blessingcurse" pk="24112"><field name="character" rel="ManyToOneRel" to="collector.character">77</field><field name="blessing_curse_ref" rel="ManyToOneRel" to="collector.blessingcurseref">37</field></object><object model="collector.blessingcurse" pk="24113"><field name="character" rel="ManyToOneRel" to="collector.character">77</field><field name="blessing_curse_ref" rel="ManyToOneRel" to="collector.blessingcurseref">18</field></object><object model="collector.blessingcurse" pk="24114"><field name="character" rel="ManyToOneRel" to="collector.character">91</field><field name="blessing_curse_ref" rel="ManyToOneRel" to="collector.blessingcurseref">14</field></object><object model="collector.blessingcurse" pk="24115"><field name="character" rel="ManyToOneRel" to="collector.character">91</field><field name="blessing_curse_ref" rel="ManyToOneRel" to="collector.blessingcurseref">38</field></object><object model="collector.blessingcurse" pk="24116"><field name="character" rel="ManyToOneRel" to="collector.character">93</field><field name="blessing_curse_ref" rel="ManyToOneRel" to="collector.blessingcurseref">17</field></object><object model="collector.blessingcurse" pk="24117"><field name="character" rel="ManyToOneRel" to="collector.character">93</field><field name="blessing_curse_ref" rel="ManyToOneRel" to="collector.blessingcurseref">42</field></object><object model="collector.blessingcurse" pk="24118"><field name="character" rel="ManyToOneRel" to="collector.character">93</field><field name="blessing_curse_ref" rel="ManyToOneRel" to="collector.blessingcurseref">2</field></object><object model="collector.blessingcurse" pk="24119"><field name="character" rel="ManyToOneRel" to="collector.character">99</field><field name="blessing_curse_ref" rel="ManyToOneRel" to="collector.blessingcurseref">17</field></object><object model="collector.blessingcurse" pk="24120"><field name="character" rel="ManyToOneRel" to="collector.character">99</field><field name="blessing_curse_ref" rel="ManyToOneRel" to="collector.blessingcurseref">42</field></object><object model="collector.blessingcurse" pk="24121"><field name="character" rel="ManyToOneRel" to="collector.character">99</field><field name="blessing_curse_ref" rel="ManyToOneRel" to="collector.blessingcurseref">45</field></object><object model="collector.blessingcurse" pk="24122"><field name="character" rel="ManyToOneRel" to="collector.character">125</field><field name="blessing_curse_ref" rel="ManyToOneRel" to="collector.blessingcurseref">60</field></object><object model="collector.blessingcurse" pk="24123"><field name="character" rel="ManyToOneRel" to="collector.character">125</field><field name="blessing_curse_ref" rel="ManyToOneRel" to="collector.blessingcurseref">14</field></object><object model="collector.blessingcurse" pk="24124"><field name="character" rel="ManyToOneRel" to="collector.character">126</field><field name="blessing_curse_ref" rel="ManyToOneRel" to="collector.blessingcurseref">28</field></object><object model="collector.blessingcurse" pk="24125"><field name="character" rel="ManyToOneRel" to="collector.character">126</field><field name="blessing_curse_ref" rel="ManyToOneRel" to="collector.blessingcurseref">15</field></object><object model="collector.blessingcurse" pk="24126"><field name="character" rel="ManyToOneRel" to="collector.character">146</field><field name="blessing_curse_ref" rel="ManyToOneRel" to="collector.blessingcurseref">28</field></object><object model="collector.blessingcurse" pk="24127"><field name="character" rel="ManyToOneRel" to="collector.character">146</field><field name="blessing_curse_ref" rel="ManyToOneRel" to="collector.blessingcurseref">15</field></object><object model="collector.blessingcurse" pk="24128"><field name="character" rel="ManyToOneRel" to="collector.character">150</field><field name="blessing_curse_ref" rel="ManyToOneRel" to="collector.blessingcurseref">50</field></object><object model="collector.blessingcurse" pk="24129"><field name="character" rel="ManyToOneRel" to="collector.character">151</field><field name="blessing_curse_ref" rel="ManyToOneRel" to="collector.blessingcurseref">37</field></object><object model="collector.blessingcurse" pk="24130"><field name="character" rel="ManyToOneRel" to="collector.character">151</field><field name="blessing_curse_ref" rel="ManyToOneRel" to="collector.blessingcurseref">18</field></object></django-objects>